hgco_download/__init__.py
hgco_download/download_cli.py
hgco_download-0.0.4.dist-info/METADATA
hgco_download-0.0.4.dist-info/WHEEL
hgco_download-0.0.4.dist-info/entry_points.txt
hgco_download-0.0.4.dist-info/top_level.txt
hgco_download-0.0.4.dist-info/RECORD
