Metadata-Version: 2.1
Name: hgco-download
Version: 0.0.4
Summary: UNKNOWN
Home-page: UNKNOWN
Author: UNKNOWN
Author-email: UNKNOWN
License: UNKNOWN
Platform: UNKNOWN
Requires-Dist: hf-lfs
